haisdk/__init__.py
haisdk/assessment.py
haisdk/audits/__init__.py
haisdk/audits/nyc_bias_audit.py
haisdk/audits/test_nyc_bias_audit.py
haisdk/config.py
haisdk/file_upload.py
haisdk/safeguard/__init__.py
haisdk/safeguard/safeguard_processor.py
haisdk/safeguard/test_safeguard.py
haisdk-0.0.18.dist-info/METADATA
haisdk-0.0.18.dist-info/WHEEL
haisdk-0.0.18.dist-info/RECORD
