Metadata-Version: 2.1
Name: haisdk
Version: 0.0.18
Summary: Holistic AI SDK Library
Author: Holistic AI
Maintainer: Engineering Team
Maintainer-email: engineering@holisticai.com
Requires-Python: >=3.8,<4.0.0
Classifier: Programming Language :: Python :: 3
Classifier: Programming Language :: Python :: 3.8
Classifier: Programming Language :: Python :: 3.9
Classifier: Programming Language :: Python :: 3.10
Classifier: Programming Language :: Python :: 3.11
Classifier: Programming Language :: Python :: 3.12
Classifier: Programming Language :: Python :: 3.13
Requires-Dist: dill (==0.3.6)
Requires-Dist: requests (==2.31.0)
